<?xml version="1.0" encoding="UTF-8"?><home><of:0000000000000001><port>1</port><bytesR>5360</bytesR><bytesS>5164</bytesS><duration>6</duration><packetsR>37</packetsR><packetsRxD>0</packetsRxD><packetsRxE>0</packetsRxE><packetsS>35</packetsS><packetsTxD>0</packetsTxD><packetsTxE>0</packetsTxE></of:0000000000000001><of:0000000000000001><port>2</port><bytesR>5164</bytesR><bytesS>5360</bytesS><duration>6</duration><packetsR>35</packetsR><packetsRxD>0</packetsRxD><packetsRxE>0</packetsRxE><packetsS>37</packetsS><packetsTxD>0</packetsTxD><packetsTxE>0</packetsTxE></of:0000000000000001><of:0000000000000001><port>1</port><bytesR>1300</bytesR><bytesS>5094</bytesS><duration>6</duration><packetsR>16</packetsR><packetsRxD>0</packetsRxD><packetsRxE>0</packetsRxE><packetsS>36</packetsS><packetsTxD>0</packetsTxD><packetsTxE>0</packetsTxE></of:0000000000000001><of:0000000000000002><port>2</port><bytesR>1300</bytesR><bytesS>5374</bytesS><duration>6</duration><packetsR>16</packetsR><packetsRxD>0</packetsRxD><packetsRxE>0</packetsRxE><packetsS>40</packetsS><packetsTxD>0</packetsTxD><packetsTxE>0</packetsTxE></of:0000000000000002><of:0000000000000002><port>3</port><bytesR>5164</bytesR><bytesS>5360</bytesS><duration>6</duration><packetsR>35</packetsR><packetsRxD>0</packetsRxD><packetsRxE>0</packetsRxE><packetsS>37</packetsS><packetsTxD>0</packetsTxD><packetsTxE>0</packetsTxE></of:0000000000000002><of:0000000000000002><port>1</port><bytesR>1300</bytesR><bytesS>5416</bytesS><duration>6</duration><packetsR>16</packetsR><packetsRxD>0</packetsRxD><packetsRxE>0</packetsRxE><packetsS>41</packetsS><packetsTxD>0</packetsTxD><packetsTxE>0</packetsTxE></of:0000000000000002><of:0000000000000002><port>2</port><bytesR>1300</bytesR><bytesS>5514</bytesS><duration>6</duration><packetsR>16</packetsR><packetsRxD>0</packetsRxD><packetsRxE>0</packetsRxE><packetsS>42</packetsS><packetsTxD>0</packetsTxD><packetsTxE>0</packetsTxE></of:0000000000000002><of:0000000000000003><port>3</port><bytesR>5360</bytesR><bytesS>5164</bytesS><duration>6</duration><packetsR>37</packetsR><packetsRxD>0</packetsRxD><packetsRxE>0</packetsRxE><packetsS>35</packetsS><packetsTxD>0</packetsTxD><packetsTxE>0</packetsTxE></of:0000000000000003></home>